{
  "url": "https://psmanual.secure.central1.com/ps_manual/Releases/PS_2433.html",
  "title": "24:33 芒聙聰 September 11, 2024",
  "section_path": "ps_manual > Releases",
  "breadcrumb": [],
  "body_text": "24:33 芒聙聰 September 11, 2024\nUpdate to Wires Data Extract Service File Specifications, Form 9327\nWe made the following changes to the Wires Data Extract Service File Specifications, Form 9327.\nDocument Library\nStatus\nWires Data Extract Service File Specifications\n9327\nChapter 4, Wires Data Extract Field Specifications\nWe updated the third column label from 芒聙聹Format芒聙聺 to 芒聙聹Contents芒聙聺.\nWe also made the following changes:\nORIGINATING SYSTEM:\n芒聙垄\nUpdated 芒聙聹LVTS芒聙聺 to 芒聙聹LYNX芒聙聺\n芒聙垄\nAdded 芒聙聹NOS芒聙聺\nRECEIVING SYSTEM:\n芒聙垄\nUpdated 芒聙聹LVTS芒聙聺 to 芒聙聹LYNX芒聙聺\n芒聙垄\nAdded 芒聙聹NOS芒聙聺\nINSTRUCTING AGENT INFORMATION:\n芒聙垄\nNew section\nREMITTANCE INFORMATION:\n芒聙垄\nUpdated the length for Line 2芒聙聯4\nSENDER FI TO RECEIVER:\n芒聙垄\nUpdated the length for Line 2芒聙聯6\nORDERING INSTITUTION:\n芒聙垄\nUpdated length column for name, address, city, and country.\n芒聙垄\nUpdated required column for address, city, and country.\n芒聙垄\nAdded Province/State, Postal/Zip, Line 1芒聙聯3.\nORDERING CUSTOMER:\n芒聙垄\nUpdated position of 芒聙聹Type芒聙聺\n芒聙垄\nUpdated length column\nSENDING CUSTOMER:\n芒聙垄\nUpdated position of 芒聙聹Type芒聙聺\n芒聙垄\nUpdated length column (except for Member number)\nBENEFICIARY CUSTOMER:\n芒聙垄\nUpdated position of 芒聙聹Type芒聙聺\n芒聙垄\nUpdated length column (except for Province/State)\n芒聙垄\nAdded samples where needed\nACCOUNT WITH INSTITUTION:\n芒聙垄\nUpdated content column and sample column for FI ID\n芒聙垄\nUpdated 芒聙聹Address芒聙聺 to 芒聙聹Street芒聙聺\n芒聙垄\nUpdated length column (except for FI ID)\n芒聙垄\nAdded Province/State, Postal/ZIP, Line 1芒聙聯3\n芒聙垄\nAdded samples where needed\nINTERMEDIARY INSTITUTION:\n芒聙垄\nAdded content, length, format and samples for Account, Name, Address 1.\n芒聙垄\nAdded Address 1 and SWIFT or ABA\nSENDER CORRESPONDENT:\n芒聙垄\nNew section\nADDITIONAL ORDERING CUSTOMER INFORMATION FOR FINTRAC REPORTING:\n芒聙垄\nUpdated 芒聙聹Postal Code芒聙聺 description to 芒聙聹Postal/ZIP芒聙聺\n芒聙垄\nUpdated length column for Account Number, First Name, Middle Name, Last Name, Street Address, City, and Postal/ZIP\nADDITIONAL SENDING CUSTOMER INFORMATION FOR FINTRAC REPORTING:\n芒聙垄\nUpdated 芒聙聹Postal Code芒聙聺 description to 芒聙聹Postal/ZIP芒聙聺\n芒聙垄\nUpdated length column for Account Number, First Name, Middle Name, Last Name, Name, Street Address, City, and Postal/ZIP\nPERSON CONDUCTING THE WIRE: (IF SET UP BY YOUR ORGANIZATION) 芒聙聯 ONLY IF TYPE IS ENTITY:\n芒聙垄\nUpdated 芒聙聹Postal Code芒聙聺 description to 芒聙聹Postal/ZIP芒聙聺\n芒聙垄\nUpdated length column for Account Number, First Name, Middle Name, Last Name, Name, Street Address, and Postal/ZIP\nADDITIONAL BENEFICIARY CUSTOMER INFORMATION FOR FINTRAC REPORTING:\n芒聙垄\nUpdated 芒聙聹Postal Code芒聙聺 description to 芒聙聹Postal/ZIP芒聙聺\n芒聙垄\nUpdated length column for Account Number, First Name, Middle Name, Last Name, Street Address, City, and Postal/ZIP\nADDITIONAL THIRD-PARTY SENDER INFORMATION FOR FINTRAC REPORTING:\n芒聙垄\nUpdated position of 芒聙聹Type芒聙聺 field\n芒聙垄\nUpdated 芒聙聹Postal Code芒聙聺 description to 芒聙聹Postal/ZIP芒聙聺\n芒聙垄\nUpdated length column for Account Number, First Name, Middle Name, Last Name, Street Address, City, and Postal/ZIP\n芒聙垄\nAdded 芒聙聹Relationship芒聙聺\nADDITIONAL THIRD-PARTY RECEIVER INFORMATION FOR FINTRAC REPORTING:\n芒聙垄\nUpdated 芒聙聹Postal Code芒聙聺 description to 芒聙聹Postal/ZIP芒聙聺\n芒聙垄\nUpdated length column for Account Number, First Name, Middle Name, Last Name, Street Address, City, and Postal/ZIP\n芒聙垄\nAdded 芒聙聹Relationship芒聙聺\nREGULATORY INFORMATION:\n芒聙垄\nAdded 芒聙聹Funded by Person or Entity?芒聙聺 and 芒聙聹Funding Method芒聙聺\nRevised\nSection 5.1, Sample XML File\nWe updated the XML file sample.\nSection 5.2, Sample Report File\nWe updated the report sample.\nChapter 6, XML Schema Definition (XSD)\nNew Chapter\nQuestions\nClient Support Services, phone\n1-888-889-7878\n, Option 1, email\nsupport@central1.com\n.",
  "links": [],
  "content_length": 3675
}