{
  "url": "https://psmanual.secure.central1.com/ps_manual/Releases/PS_2214.html",
  "title": "22:14 — April 25, 2022",
  "section_path": "ps_manual > Releases",
  "breadcrumb": [],
  "body_text": "22:14 — April 25, 2022\nInterac\ne-Transfer\n®\nMetrics Report\nWe updated the Payment Solutions manual with a description of the new Interac e-Transfer Metrics Report. This report is not used for operational purposes (i.e., settlement, reconciliation, or tracing). It contains information that provides business intelligence on the performance of the service through your financial institution and market comparison on certain metrics. See the\nsecure site announcement\nfor more details and FAQs.\nElectronic Transactions Volume\nInterac e-Transfer\n®\nLimits, Settlement, Tracing, and Reports Part\nSection 7.1, Overview of Interac e-Transfer Reports\nWe added a paragraph describing the new Interac e-Transfer Metrics Report.\nQuestions\nClient Support Services, phone\n1-888-889-7878\n, Option 1, email\nsupport@central1.com\n.",
  "links": [],
  "content_length": 817
}