{
  "url": "https://psmanual.secure.central1.com/ps_manual/Electronic%20Transactions/atm_and_pos.4.06.html",
  "title": "6 ATM Deposits – Issuer Procedures",
  "section_path": "ps_manual > Electronic%20Transactions",
  "breadcrumb": [],
  "body_text": "6\tATM Deposits – Issuer Procedures\n6.1\tOverview of ATM Deposit Procedures for the Issuer\nThe financial institution that issues the debit card is the issuer. Cardholders can deposit cheques at an ATM owned by\nany participant of THE EXCHANGE\n®\n, or\nany other Canadian financial institution that participates in the ACCULINK\n®\nnetwork.\nSee Section 5.3, Route and Transit and AFT Adjustment Account Listings, for procedures on obtaining the appropriate route and transit listings.\n6.2\tReceiving Notification of Exception Deposits\nThe acquirer of a deposit must notify the issuer immediately by phone or fax in the situations specified below. This notification allows you to hold funds on the deposit if this is your financial institution’s policy. The acquirer must send notification no later than the business day following the settlement day of the deposit.\nIf you receive a phone call asking for confirmation, give the caller your name. If you receive a fax asking for confirmation, immediately send back an acknowledging reply, giving your name and phone number. Keep a record of all notifications.\nTHE EXCHANGE Exception Deposits\nThe Canadian Exchange Network Operating Rules stipulate that the acquirer must notify the cardholder’s financial institution as follows:\nIf the deposit value is $5,000 or greater, fax\n−\na copy of the front and back of the singular cheque that is valued at $5,000 or greater,\n−\na confirmation of a cash deposit greater than $5,000, if applicable, and\n−\na duly completed EXCHANGE Network Advice Form.\nIf the deposit value is $10,000 or greater, fax\n−\na copy of the front and back of all cheques that make up all or part of the deposit,\n−\na confirmation of a cash deposit greater than $5,000, if applicable, and\n−\na duly completed EXCHANGE Network Advice Form.\nIf it’s evident that a cheque has been materially altered, regardless of whether the alteration is initialed, fax\n−\na copy of the front and back of the cheque, and\n−\na duly completed EXCHANGE Network Advice Form.\nIf a debit or credit adjustment to a deposit is required because the difference is $20.01 or greater, fax a duly completed EXCHANGE Network Advice Form.\nIf an empty deposit envelope is received, fax a duly completed EXCHANGE Network Advice Form.\nACCULINK Exception Deposits\nACCULINK ATM Operating Policies and Procedures stipulate that the acquirer must notify the issuer if:\nA deposit contains an error of $20.01 or greater.\nAn empty deposit envelope is received.\nThe deposit value is $10,000 or greater.\nNote:\tA copy of the front and back of all cheques that make up all or part of the deposit must be provided.\nA cheque isn’t encoded with the route and transit numbers.\nLiability\nIf you receive a phone call or fax, you must acknowledge receipt either by exchanging names (if by phone) or by replying to the fax.\nIf the acquirer fails to give you notification, the acquirer may be responsible for any losses. However, if you fail to acknowledge the notification, the acquirer may not be responsible.\n6.3\tChargebacks (Issuer)\nThe Canadian Exchange Network Operating Rules and the ACCULINK ATM Operating Policies and Procedures stipulate that if an acquirer receives a chargeback on a deposit, the acquirer must notify you by phone or confirmed facsimile, either\nbefore the close of business on the day they received notice of the chargeback, or\nthe next business day that you are open.\n6.4\tBill Payments (Issuer)\nIf one of your customers makes a bill payment at another financial institution’s ATM and the payment is correctly keyed as a “payment,” the acquirer will either remit the payment directly to the vendor or forward the payment and stub to you for processing.\nIf a bill payment is incorrectly keyed as a “deposit,” the acquirer will send it back to you as an adjustment. See Chapter 11, Receiving ATM Traces and Adjustments.\nEND",
  "links": [],
  "content_length": 3880
}