{
  "url": "https://psmanual.secure.central1.com/ps_manual/Releases/PS_2435.html",
  "title": "24:35 ГўВЂВ” September 16, 2024",
  "section_path": "ps_manual > Releases",
  "breadcrumb": [],
  "body_text": "24:35 ГўВЂВ” September 16, 2024\nUpdate to Country-Specific Guidelines and Instructions, Form 3597\nWe updated the Country-Specific Guidelines and Instructions, Form 3597. These changes were also made in the Wires application.\nDocument Library\nStatus\nCountry-Specific Guidelines and Instructions\n3597\nWe added sanctions/warning messages for the following countries:\nГўВЂВў\nAlbania\nГўВЂВў\nComoros\nГўВЂВў\nCuracao\nГўВЂВў\nDjibouti\nГўВЂВў\nGuatemala\nГўВЂВў\nGuyana\nГўВЂВў\nLaos\nГўВЂВў\nLiberia\nГўВЂВў\nMonaco\nГўВЂВў\nNamibia\nГўВЂВў\nSierra Leone\nГўВЂВў\nSint Maarten\nГўВЂВў\nSuriname\nWe updated sanctions/warning messages for the following countries:\nГўВЂВў\nBelarus\nГўВЂВў\nChina\nГўВЂВў\nEthiopia\nГўВЂВў\nF.Y.R. Macedonia\nГўВЂВў\nMontenegro\nГўВЂВў\nSerbia\nГўВЂВў\nTunisia\nWe removed sanctions/warning messages for the following countries:\nГўВЂВў\nBahamas\nГўВЂВў\nBelize\nГўВЂВў\nBrazil\nГўВЂВў\nCayman Islands\nГўВЂВў\nIsrael\nГўВЂВў\nSeychelles\nГўВЂВў\nTurks and Caicos\nWe added payment instructions for the following countries.\nГўВЂВў\nAustralia\nГўВЂВў\nDenmark\nWe updated the payment instructions for the following countries:\nГўВЂВў\nBahrain\nГўВЂВў\nKuwait\nГўВЂВў\nPakistan\nГўВЂВў\nUganda\nГўВЂВў\nViet Nam\nRevised\nQuestions\nClient Support Services, phone\n1-888-889-7878\n, Option 1, email\nsupport@central1.com\n.",
  "links": [],
  "content_length": 1168
}