{
  "url": "https://psmanual.secure.central1.com/ps_manual/Releases/PS_2050.html",
  "title": "20:50 — December 31, 2020",
  "section_path": "ps_manual > Releases",
  "breadcrumb": [],
  "body_text": "20:50 — December 31, 2020\nFX Notes Plus Part Update\nExchange Bank of Canada has notified Central 1 that effective January 1, 2020, only USD currency is available for the purchase of drafts through the FX Notes Plus application.\nThe FX Notes Plus videos have been revised on the\nFX Notes Plus Training Videos\npage.\nWe updated the FX Notes Plus Part in the Payment Solutions Manual as described in the table below.\nCurrency Volume\nFX Notes Plus Part\nSection 7.2, Types of Currency Available for Notes and Drafts\nSection 7.6, Cancelling Foreign Currency Orders\nSection 7.7, Selling Drafts\nSection 7.8, Reviewing Pending Drafts\nWe revised text and updated images as applicable.\nQuestions\nClient Support Services, phone\n1-888-889-7878\n, Option 1, email\nsupport@central1.com\n.",
  "links": [],
  "content_length": 772
}