{
  "url": "https://psmanual.secure.central1.com/ps_manual/Releases/FYI_May_2025.html",
  "title": "FYI — May 2025",
  "section_path": "ps_manual > Releases",
  "breadcrumb": [],
  "body_text": "FYI — May 2025\nFYI ─ May 2025\nThe following updates were made to the Payment Solutions Manual.\nCentral 1 Banking Services Volume\nCentral 1 Current Accounts Part\nSection 1.9, Central 1 Current Accounts Document Library\nWe added the Treasury Connect User Guide to the document library.\nSection 4.1, Overview of Inter-Branch and Central 1 Corporate Client Transfers\nWe added a note that authorized Treasury Connect Users can transfer funds between Central 1 accounts of the same currency via Treasury Connect.\nDocument Library\nStatus\nPayor’s PAD Agreement\n1696\nWe updated the form to include e-signature fields and applied improved accessibility standards.\nRevised\nQuestions\nCentral 1, Client Support Services, phone\n1-888-889-7878\n, Option 1, email\nsupport@central1.com\n.",
  "links": [],
  "content_length": 775
}