{
  "url": "https://psmanual.secure.central1.com/ps_manual/Releases/PS_2202.html",
  "title": "22:02 — January 12, 2022",
  "section_path": "ps_manual > Releases",
  "breadcrumb": [],
  "body_text": "22:02 — January 12, 2022\nCorrection to the Digital & Payment Services Class A Fee Schedule, Form 2725\nWe updated the Deposit Anywhere pricing in multiple sections of the Digital & Payment Services Class A Fee Schedule, Form 2725. The fees published on December 30, 2021, inadvertently showed a price increase when there was no actual change to the 2021 fees.\nQuestions\nClient Support Services, phone\n1-888-889-7878\n, Option 1, email\nsupport@central1.com\n.",
  "links": [],
  "content_length": 457
}